{
  "position_id": 1199,
  "market_id": "btc-updown-5m-1776414300",
  "question": "Bitcoin Up or Down - April 17, 4:25AM-4:30AM ET",
  "side": "Down",
  "signal_score": 0.20912249972463082,
  "correct": false,
  "entry_price": 0.11,
  "exit_price": 0.0,
  "log_return": -10.0,
  "size": 1.5,
  "pnl": -1.5,
  "fees": 0.02402999999999995,
  "gain_pct": -1.0,
  "weight_version": "weights_v001",
  "category": "crypto-5min",
  "indicator_snapshot": {
    "rsi": {
      "rsi": 78.75,
      "score": -0.5041,
      "norm_score": -0.11174846818784309
    },
    "macd": {
      "macd": 5.7432,
      "signal": -2.1593,
      "histogram": 7.9025,
      "score": 0.5273,
      "norm_score": 0.986656346304865
    },
    "stochastic": {
      "k": 100.0,
      "d": 75.95,
      "score": -1.0,
      "norm_score": -0.9206252128008142
    },
    "ema": {
      "trend": "bullish",
      "fast_ema": 75122.02609831865,
      "slow_ema": 75108.39946769061
    },
    "obv": {
      "obv_slope": 0.0,
      "price_slope": 5.7767,
      "score": 0.0016,
      "norm_score": 1.3630956359506838
    },
    "vwap": {
      "vwap": 74853.39,
      "deviation": 1.703,
      "score": -0.5109,
      "norm_score": -1.2548165449569573
    },
    "atr": {
      "atr": 23.17,
      "passes": true,
      "reason": "ok"
    },
    "weights": {
      "rsi": 0.2,
      "macd": 0.25,
      "stochastic": 0.2,
      "obv": 0.15,
      "vwap": 0.2,
      "entry_threshold": 0.6
    },
    "trade_context": {
      "btc_price": 75161.25,
      "strike_price": 75082.45122849556,
      "seconds_remaining": 135.504577,
      "market_price_up": 0.87,
      "market_price_down": 0.12,
      "model_probability_raw": 0.20912249972463082,
      "model_probability": 0.20912249972463082,
      "edge": 0.08912249972463082,
      "momentum_score": -0.0063096132203041,
      "atr": 23.17,
      "size": 1.5,
      "flow_score": 0.0616,
      "flow_book_imbalance": 0.4716,
      "flow_trade_count": 200,
      "spot_flow_signal": 0.6298742145756788,
      "wall_pressure": 0.0,
      "iv_ratio": 1.9343075086207144,
      "prev_resolution_margin": -54.16617674297595,
      "bybit_perp_price": 75100.0,
      "funding_rate": 3.238e-05,
      "depth_usd_top20": 373201.2571496,
      "entry_phase": "late",
      "flip_count": 1,
      "is_flip": true,
      "cvd_120s": 0.00525,
      "taker_ratio_60s": 1.0,
      "volume_surge": false,
      "liquidation_pressure": 0.0,
      "gex_signal": 1.0,
      "gex_regime": "stabilizing",
      "cvd_acceleration": -0.00010955555555555554,
      "clob_velocity_up": 0.012636239457759648,
      "clob_velocity_down": -0.012636239457759648,
      "coinbase_btc": 75161.25,
      "regime_state": "volatile",
      "regime_kelly_mult": 0.7,
      "sprt_confidence": 0.0,
      "sprt_status": "SKIP",
      "signal_consensus": 0.6,
      "adverse_selection_30s": 0.5625,
      "alpha_decay_rate": 0.0028947982489845726,
      "garch_vol_ratio": 2.0,
      "crowd_bias": {
        "flb": 0.0222,
        "recency_fade": 0.0,
        "round_number_dampening": 0.96,
        "composite_logit_adjustment": 0.0222
      },
      "oracle_divergence": 13.163702536417986,
      "edge_realization_ratio": 3.4738343995213246
    }
  },
  "exit_reason": "resolution",
  "timestamp": "2026-04-17T08:35:08.757971+00:00"
}