{
  "position_id": 280,
  "market_id": "btc-updown-5m-1776176100",
  "question": "Bitcoin Up or Down - April 14, 10:15AM-10:20AM ET",
  "side": "Down",
  "signal_score": 0.6502115833219826,
  "correct": true,
  "entry_price": 0.59,
  "exit_price": 0.66,
  "log_return": 0.11211729812070621,
  "size": 1.46,
  "pnl": 0.1512449491525425,
  "fees": 0.020697000000000118,
  "gain_pct": 0.103592,
  "weight_version": "weights_v001",
  "category": "crypto-5min",
  "indicator_snapshot": {
    "rsi": {
      "rsi": 57.2,
      "score": -0.1079,
      "norm_score": -0.20753827404183514
    },
    "macd": {
      "macd": 41.7623,
      "signal": 43.9783,
      "histogram": -2.216,
      "score": -0.04,
      "norm_score": -0.2607382172210849
    },
    "stochastic": {
      "k": 62.14,
      "d": 60.17,
      "score": -0.1214,
      "norm_score": 0.2416634289731544
    },
    "ema": {
      "trend": "bullish",
      "fast_ema": 75563.27567993454,
      "slow_ema": 75540.60922690525
    },
    "obv": {
      "obv_slope": 0.0,
      "price_slope": -14.62,
      "score": 0.0002,
      "norm_score": 0.0006647436862099082
    },
    "vwap": {
      "vwap": 74972.76,
      "deviation": 1.6426,
      "score": -0.4928,
      "norm_score": 0.02654695823192553
    },
    "atr": {
      "atr": 91.92,
      "passes": true,
      "reason": "ok"
    },
    "weights": {
      "rsi": 0.2,
      "macd": 0.25,
      "stochastic": 0.2,
      "obv": 0.15,
      "vwap": 0.2,
      "entry_threshold": 0.6
    },
    "trade_context": {
      "btc_price": 75572.23,
      "strike_price": 75611.01220296757,
      "seconds_remaining": 250.39284,
      "market_price_up": 0.4,
      "market_price_down": 0.59,
      "model_probability_raw": 0.6502115833219826,
      "model_probability": 0.6502115833219826,
      "edge": 0.06021158332198262,
      "momentum_score": -0.05295042011969078,
      "atr": 91.92,
      "size": 1.46,
      "flow_score": -0.0637,
      "flow_book_imbalance": -0.1337,
      "flow_trade_count": 200,
      "spot_flow_signal": -0.06052388350842276,
      "wall_pressure": 0.0,
      "iv_ratio": 0.5113341270229941,
      "prev_resolution_margin": 0.0,
      "bybit_perp_price": 75470.0,
      "funding_rate": 3.798e-05,
      "depth_usd_top20": 300639.7097194001,
      "entry_phase": "normal",
      "flip_count": 0,
      "is_flip": false,
      "cvd_120s": -0.0009599999999999999,
      "taker_ratio_60s": 0.3622291021671827,
      "volume_surge": false,
      "liquidation_pressure": 0.0,
      "gex_signal": 1.0,
      "gex_regime": "stabilizing",
      "cvd_acceleration": 1.9777777777777778e-05,
      "clob_velocity_up": 0.0,
      "clob_velocity_down": 0.0,
      "coinbase_btc": 75572.23,
      "regime_state": "mean_reverting",
      "regime_kelly_mult": 0.8,
      "sprt_confidence": 0.0,
      "sprt_status": "SKIP",
      "signal_consensus": 1.3,
      "adverse_selection_30s": 0.5,
      "alpha_decay_rate": 0.0005682677242758291,
      "garch_vol_ratio": 2.0,
      "crowd_bias": {
        "flb": 0.0,
        "recency_fade": 0.0,
        "round_number_dampening": 1.0,
        "composite_logit_adjustment": 0.0
      },
      "oracle_divergence": 2.555640000005951,
      "edge_realization_ratio": 1.0
    }
  },
  "exit_reason": "scalp",
  "timestamp": "2026-04-14T14:16:10.662674+00:00"
}