{
  "position_id": 8450,
  "market_id": "btc-updown-5m-1782826500",
  "question": "Bitcoin Up or Down - June 30, 9:35AM-9:40AM ET",
  "side": "Down",
  "signal_score": 0.6850094109328271,
  "correct": true,
  "entry_price": 0.58,
  "exit_price": 0.8,
  "log_return": 0.32158362412746233,
  "size": 19.57,
  "pnl": 6.498508675862077,
  "fees": 0.5753579999999984,
  "gain_pct": 0.332065,
  "realized_edge": 0.105,
  "fill_slippage": 0.0,
  "indicator_snapshot": {
    "atr": {
      "atr": 99.55,
      "passes": true,
      "reason": "ok",
      "candle_ts": 1782826500000
    },
    "trade_context": {
      "btc_price": 58215.46,
      "strike_price": 58282.71482235159,
      "seconds_remaining": 294.912307,
      "market_price_up": 0.43,
      "market_price_down": 0.58,
      "closes_tail": [
        58380.84,
        58336.66
      ],
      "model_probability": 0.6850094109328271,
      "model_probability_raw": 0.6850094109328271,
      "edge": 0.10500941093282712,
      "atr": 99.55,
      "atr_rolling_20": 63.4425,
      "atr_long_term_mean": 38.4748,
      "size": 19.57,
      "prev_resolution_margin": -162.5268157981991,
      "flow_score": 0.4198,
      "spot_flow_signal": -0.6288007737858848,
      "regime_autocorr": -0.0026,
      "regime_direction": -1.0,
      "entry_phase": "normal",
      "flip_count": 0,
      "is_flip": false,
      "depth_usd_top20": 212979.05848630005,
      "coinbase_cvd_60s": -56.3855,
      "coinbase_taker_60s": 0.1606,
      "coinbase_taker_n": 1986,
      "cross_venue_gap": -103.26,
      "fast_realized_vol_60s": 0.000259,
      "clob_depth_top5_up_usd": 19930.22,
      "clob_depth_top5_down_usd": 20024.88,
      "clob_book_age_s": 0.135,
      "adverse_rate_at_30s": 0.47058823529411764,
      "adverse_kelly_mult": 0.969,
      "token_id_up": "99286145387832927905535784373419676046128194237499952807743073360054967923334",
      "token_id_down": "74176017441506766416095053435499519613365414893102667935933562383711143924665"
    }
  },
  "exit_reason": "scalp",
  "seconds_remaining_at_exit": 51.976628,
  "edge_decay": {
    "midprice_at_fill": 0.575,
    "deltas": {
      "5s": 0.01,
      "10s": 0.02,
      "15s": -0.08,
      "30s": -0.07,
      "60s": 0.125
    },
    "resolved_windows": 5
  },
  "exit_timestamp": "2026-06-30T13:39:08.665211+00:00",
  "timestamp": "2026-06-30T13:39:08.665211+00:00"
}