{
  "position_id": 3229,
  "market_id": "btc-updown-5m-1781276100",
  "side": "Up",
  "timestamp": "2026-06-12T15:03:20.041749+00:00",
  "actual": {
    "exit_reason": "hold",
    "exit_price": 1.0,
    "pnl": 21.247136,
    "gain_pct": 1.048723
  },
  "counterfactual": {
    "exit_reason": "hypothetical_scalp",
    "exit_price": 0.58,
    "pnl": 3.106359,
    "gain_pct": 0.153325
  },
  "delta_pnl": 18.140777,
  "hold_was_optimal": true,
  "context_at_worst_moment": {
    "holding_edge": -0.05751190085604707,
    "model_prob": 0.5224880991439529,
    "market_price": 0.58,
    "seconds_remaining": 177.163898,
    "exit_threshold_used": -0.1,
    "strike_price": 63878.009197524865,
    "btc_at_worst": 63884.0,
    "flow_score": -0.2224,
    "spot_flow_signal": 0.49890705990612755,
    "regime": "unknown",
    "btc_distance_atr": 0.052,
    "worst_at": 1781276222.8379202,
    "coinbase_cvd_60s": 15.685,
    "coinbase_taker_60s": 0.7875,
    "coinbase_taker_n": 1041,
    "cross_venue_gap": -59.99,
    "fast_realized_vol_60s": 0.000144
  }
}