{
  "position_id": 5352,
  "market_id": "btc-updown-5m-1781836200",
  "side": "Down",
  "timestamp": "2026-06-19T02:43:47.941755+00:00",
  "actual": {
    "exit_reason": "scalp",
    "exit_price": 0.35,
    "pnl": -1.403316,
    "gain_pct": -0.327878
  },
  "counterfactual": {
    "resolution_price": 0.0,
    "pnl": -4.28,
    "gain_pct": -1.0
  },
  "delta_pnl": -2.876684,
  "scalp_was_optimal": true,
  "context_at_scalp": {
    "holding_edge": -0.08049868209671851,
    "model_prob": 0.26950131790328147,
    "market_price": 0.35,
    "seconds_remaining": 225.80905,
    "exit_threshold_used": -0.1,
    "effective_exit_threshold": -0.07024416408291523,
    "loss_cut": false,
    "entry_price": 0.5,
    "fee_rate": 0.07,
    "strike_price": 62888.10567273656,
    "btc_at_scalp": 62900.6,
    "btc_at_expiry": 62929.96087054326,
    "chainlink_price_to_beat": 62888.766965009316,
    "chainlink_final_price": 62929.96087054326,
    "flow_score": -0.1914,
    "spot_flow_signal": -0.02140465912374525,
    "regime": "unknown",
    "btc_distance_atr": 0.685,
    "coinbase_cvd_60s": -0.1437,
    "coinbase_taker_60s": 0.4599,
    "coinbase_taker_n": 218,
    "cross_venue_gap": -65.38,
    "fast_realized_vol_60s": 3.1e-05
  }
}