{
  "position_id": 719,
  "market_id": "btc-updown-5m-1776284100",
  "side": "Down",
  "weight_version": "weights_v001",
  "timestamp": "2026-04-15T20:20:30.319540+00:00",
  "actual": {
    "exit_reason": "scalp",
    "exit_price": 0.95,
    "pnl": 6.539543,
    "gain_pct": 0.958877
  },
  "counterfactual": {
    "resolution_price": 1.0,
    "pnl": 7.255344,
    "gain_pct": 1.063833
  },
  "delta_pnl": 0.715801,
  "scalp_was_optimal": false,
  "context_at_scalp": {
    "holding_edge": -0.2183969771827774,
    "model_prob": 0.7316030228172226,
    "market_price": 0.95,
    "seconds_remaining": 162.667826,
    "exit_threshold_used": -0.05,
    "strike_price": 74687.37299,
    "btc_at_scalp": 74579.1,
    "btc_at_expiry": 74602.57,
    "chainlink_price_to_beat": null,
    "chainlink_final_price": null
  }
}