{
  "position_id": 7737,
  "market_id": "btc-updown-5m-1779237900",
  "side": "Up",
  "timestamp": "2026-05-20T00:56:03.975585+00:00",
  "actual": {
    "exit_reason": "scalp",
    "exit_price": 0.22,
    "pnl": -9.013661,
    "gain_pct": -0.533037
  },
  "counterfactual": {
    "resolution_price": 1.0,
    "pnl": 19.493554,
    "gain_pct": 1.152783
  },
  "delta_pnl": 28.507215,
  "scalp_was_optimal": false,
  "context_at_scalp": {
    "holding_edge": 0.34045660093393204,
    "model_prob": 0.560456600933932,
    "market_price": 0.22,
    "seconds_remaining": 89.998452,
    "exit_threshold_used": -0.07,
    "strike_price": 76643.48400551431,
    "btc_at_scalp": 76611.73,
    "btc_at_expiry": 76665.02289278914,
    "chainlink_price_to_beat": 76647.94137702996,
    "chainlink_final_price": 76665.02289278914,
    "flow_score": -0.0876,
    "spot_flow_signal": 0.04085409255999713,
    "regime": "neutral",
    "btc_distance_atr": -0.647
  }
}